README.rst
setup.py
pytest_report/__init__.py
pytest_report/atom.py
pytest_report/dump.py
pytest_report/plugin.py
pytest_report.egg-info/PKG-INFO
pytest_report.egg-info/SOURCES.txt
pytest_report.egg-info/dependency_links.txt
pytest_report.egg-info/entry_points.txt
pytest_report.egg-info/requires.txt
pytest_report.egg-info/top_level.txt