Metadata-Version: 1.1
Name: pytest-report
Version: 0.2.1
Summary: Creates json report that is compatible with atom.io's linter message format 
Home-page: https://github.com/wandel/pytest-atom
Author: Brett Wandel
Author-email: brett.wandel@live.com.au
License: MIT
Platform: UNKNOWN
Classifier: Development Status :: 4 - Beta
Classifier: Framework :: Pytest
Classifier: Intended Audience :: Developers
Classifier: Topic :: Software Development :: Testing
Classifier: Programming Language :: Python
Classifier: Programming Language :: Python :: 3
Classifier: Programming Language :: Python :: 3.3
Classifier: Programming Language :: Python :: 3.4
Classifier: Programming Language :: Python :: 3.5
Classifier: Programming Language :: Python :: Implementation :: CPython
Classifier: Operating System :: OS Independent
Classifier: License :: OSI Approved :: MIT License
